pythest/__init__.py
pythest/main.py
pythest-0.1.1.dist-info/LICENSE
pythest-0.1.1.dist-info/METADATA
pythest-0.1.1.dist-info/WHEEL
pythest-0.1.1.dist-info/entry_points.txt
pythest-0.1.1.dist-info/top_level.txt
pythest-0.1.1.dist-info/RECORD
