Metadata-Version: 2.1
Name: pythest
Version: 0.1.1
Summary: Bonjour
Home-page: https://github.com/bemaudettest/pythest
Author: Ton Nom
Author-email: ton.email@example.com
Classifier: Programming Language :: Python :: 3
Classifier: License :: OSI Approved :: MIT License
Classifier: Operating System :: OS Independent
Requires-Python: >=3.6
License-File: LICENSE
